avrocli/__init__.py
avrocli/main.py
avro.py_cli-2023.8.3.dist-info/LICENSE
avro.py_cli-2023.8.3.dist-info/METADATA
avro.py_cli-2023.8.3.dist-info/WHEEL
avro.py_cli-2023.8.3.dist-info/entry_points.txt
avro.py_cli-2023.8.3.dist-info/top_level.txt
avro.py_cli-2023.8.3.dist-info/RECORD
