Metadata-Version: 2.1
Name: avro.py-cli
Version: 2023.8.3
Summary: A simple CLI for avro.py to ease Bangla phonetic workflow inside your terminal.
Home-page: https://github.com/hitblast/avro.py-cli
Author: HitBlast
Author-email: hitblastlive@gmail.com
License: MIT
Keywords: python,avro,avro phonetic,bangla,bangla phonetics,bengali,bengali phonetics
Classifier: Intended Audience :: Developers
Classifier: License :: OSI Approved :: MIT License
Classifier: Operating System :: OS Independent
Classifier: Programming Language :: Python :: 3.8
Classifier: Programming Language :: Python :: 3.9
Classifier: Programming Language :: Python :: 3.10
Classifier: Programming Language :: Python :: 3.11
Classifier: Topic :: Software Development :: Libraries :: Python Modules
Requires-Python: >=3.8
License-File: LICENSE
Requires-Dist: click
Requires-Dist: rich
Requires-Dist: pyclip
Requires-Dist: avro.py
